byted_pycton_extensions/__init__.py
byted_pycton_extensions-0.0.1.dist-info/METADATA
byted_pycton_extensions-0.0.1.dist-info/WHEEL
byted_pycton_extensions-0.0.1.dist-info/top_level.txt
byted_pycton_extensions-0.0.1.dist-info/RECORD
